setup.py
bmywp/__init__.py
bmywp/account.py
bmywp/alarm.py
bmywp/config.py
bmywp/exchange.py
bmywp/forecast.py
bmywp/index.py
bmywp/main.py
bmywp/strategy.py
bmywp/test.py
bmywp/utils.py
bmywp.egg-info/PKG-INFO
bmywp.egg-info/SOURCES.txt
bmywp.egg-info/dependency_links.txt
bmywp.egg-info/not-zip-safe
bmywp.egg-info/top_level.txt