Metadata-Version: 1.0
Name: bmywp
Version: 0.1
Summary: BymBit Rest API wrapper
Home-page: https://github.com/abdesslem/bmywp
Author: Abdesslem Amri
Author-email: amriabdesslem@gmail.com
License: GPLv3.0
Platform: UNKNOWN
